imgannotator/__init__.py
imgannotator/cli.py
imgannotator/filters.py
imgannotator/metadata.py
tests/test_filters.py
tests/test_metadata.py
imgannotator-0.1.0.dist-info/METADATA
imgannotator-0.1.0.dist-info/WHEEL
imgannotator-0.1.0.dist-info/entry_points.txt
imgannotator-0.1.0.dist-info/top_level.txt
imgannotator-0.1.0.dist-info/RECORD
